arlulacore/__init__.py
arlulacore/archive.py
arlulacore/arlula.py
arlulacore/auth.py
arlulacore/campaign.py
arlulacore/collections.py
arlulacore/common.py
arlulacore/dataset.py
arlulacore/exception.py
arlulacore/list.py
arlulacore/order.py
arlulacore/orders.py
arlulacore/resource.py
arlulacore/tasking.py
arlulacore/util.py
arlulacore-4.0.1.dist-info/LICENSE
arlulacore-4.0.1.dist-info/METADATA
arlulacore-4.0.1.dist-info/WHEEL
arlulacore-4.0.1.dist-info/top_level.txt
arlulacore-4.0.1.dist-info/RECORD
