Metadata-Version: 2.1
Name: arlulacore
Version: 4.0.1
Summary: A package to facilitate access to the Arlula Imagery Marketplace API
Home-page: https://github.com/Arlula/python-core-sdk.git
Author: Arlula
Author-email: tech@arlula.com
Classifier: Programming Language :: Python :: 3
Classifier: License :: OSI Approved :: MIT License
Classifier: Operating System :: OS Independent
License-File: LICENSE
Requires-Dist: requests
